mcp_openapi/__init__.py
mcp_openapi/api_client.py
mcp_openapi/async_typer.py
mcp_openapi/cli.py
mcp_openapi/server.py
mcp_openapi/settings.py
mcp_openapi-0.0.2.dist-info/METADATA
mcp_openapi-0.0.2.dist-info/WHEEL
mcp_openapi-0.0.2.dist-info/entry_points.txt
mcp_openapi-0.0.2.dist-info/RECORD
