Metadata-Version: 2.4
Name: mcp-openapi
Version: 0.0.2
Summary: A Model Context Protocol bridge to OpenAPI servers
Project-URL: Homepage, https://github.com/rmasters/mcp-openapi
Project-URL: Issues, https://github.com/rmasters/mcp-openapi/issues
Author-email: Ross Masters <ross@rossmasters.com>
Requires-Python: >=3.13
Requires-Dist: aiohttp>=3.11.12
Requires-Dist: fastapi>=0.115.8
Requires-Dist: mcp[cli]>=1.3.0
Requires-Dist: openapi3-parser>=1.1.19
Requires-Dist: pydantic-settings>=2.8.0
Requires-Dist: pyyaml>=6.0.2
Requires-Dist: typer>=0.15.1
